pyallffs/AbsolutePearsonCorrelationCalculator.py
pyallffs/Chi2ScoreCalculator.py
pyallffs/CramersVCalculator.py
pyallffs/EuclideanDistanceCalculator.py
pyallffs/FilterFeatureSelectionComparison.py
pyallffs/FisherScoreCalculator.py
pyallffs/GainRatioCalculator.py
pyallffs/InformationGainCalculator.py
pyallffs/KruskalWallisCalculator.py
pyallffs/LaplacianCalculator.py
pyallffs/LeastSquaresCalculator.py
pyallffs/MarkovBlanketCalculator.py
pyallffs/MaximumLikelihoodCalculator.py
pyallffs/MutualInformationCalculator.py
pyallffs/ReliefCalculator.py
pyallffs/SymmetricUncertaintyCoefficientCalculator.py
pyallffs/TScoreCalculator.py
pyallffs/WelchTScoreCalculator.py
pyallffs/__init__.py
pyallffs/mRMRCalculator.py
pyallffs-0.1.dist-info/LICENSE
pyallffs-0.1.dist-info/METADATA
pyallffs-0.1.dist-info/WHEEL
pyallffs-0.1.dist-info/top_level.txt
pyallffs-0.1.dist-info/RECORD
