Metadata-Version: 2.1
Name: pyallffs
Version: 0.1
Summary: All Filter Feature Selection Methods
Author-email: Tohid Yousefi <tohid.yousefi@hotmail.com>, Özlem Varlıklar <aktas.ozlem@deu.edu.tr>
Maintainer-email: Özlem Varlıklar <aktas.ozlem@deu.edu.tr>
Project-URL: Homepage, https://github.com/tohid-yousefi/pyallffs
Project-URL: Website, https://tohid.com.tr
Classifier: Programming Language :: Python :: 3
Classifier: License :: OSI Approved :: MIT License
Classifier: Operating System :: OS Independent
Requires-Python: >=3.8
License-File: LICENSE
